sqlask/__init__.py
sqlask/bin/sqlask
sqlask/conf/templates/app/models.py.template
sqlask/conf/templates/app/routes.py.template
sqlask/conf/templates/app/serializers.py.template
sqlask/conf/templates/app/viewsets.py.template
sqlask/conf/templates/project/dev.py.template
sqlask/conf/templates/project/server.py.template
sqlask/conf/templates/project/zappa_settings.json.template
sqlask/core/__init__.py
sqlask/core/management/__init__.py
sqlask/core/management/base.py
sqlask/core/management/commands/__init__.py
sqlask/core/management/commands/app.py
sqlask/core/management/commands/help.py
sqlask/core/management/commands/migrate.py
sqlask/core/management/commands/project.py
sqlask/core/management/commands/seed.py
sqlask/core/management/commands/shell.py
sqlask-1.0.4.data/scripts/sqlask
sqlask-1.0.4.dist-info/METADATA
sqlask-1.0.4.dist-info/RECORD
sqlask-1.0.4.dist-info/WHEEL
sqlask-1.0.4.dist-info/entry_points.txt
sqlask-1.0.4.dist-info/top_level.txt
