Metadata-Version: 2.1
Name: sqlask
Version: 1.0.4
Summary: lightweight python framework for webapplications
Home-page: http://github.com/codejunker1/sqlask
Author: Venkata Sai Katepalli
Author-email: venkatasaisoft@gmail.com
License: MIT
Platform: UNKNOWN
Classifier: Programming Language :: Python :: 3
Classifier: License :: OSI Approved :: MIT License
Classifier: Operating System :: OS Independent
Requires-Dist: flasgger (==0.8.0)
Requires-Dist: Flask (==0.12.2)
Requires-Dist: Flask-Cors (==3.0.3)
Requires-Dist: Flask-JWT (==0.3.2)
Requires-Dist: Flask-RESTful (==0.3.6)
Requires-Dist: marshmallow (==2.15.0)
Requires-Dist: bcrypt (==3.1.4)
Requires-Dist: pandas (==0.23.0)
